middlefield/__init__.py
middlefield/__main__.py
middlefield/_api.py
middlefield/_main.py
middlefield/_version.py
middlefield/test/__init__.py
middlefield/test/test_api.py
middlefield/test/test_main.py
middlefield-18.9.0.dist-info/METADATA
middlefield-18.9.0.dist-info/RECORD
middlefield-18.9.0.dist-info/WHEEL
middlefield-18.9.0.dist-info/entry_points.txt
middlefield-18.9.0.dist-info/top_level.txt
